{
  "version": "7.0.4",
  "flags": {},
  "shapes": [
    {
      "label": "windshield",
      "points": [
        [
          573.4136355968493,
          429.75015247265225
        ],
        [
          547.6108833032713,
          430.32354696806505
        ],
        [
          498.7072135785007,
          426.48868458274404
        ],
        [
          464.7072135785007,
          424.48868458274404
        ],
        [
          433.7072135785007,
          417.48868458274404
        ],
        [
          410.2072135785007,
          402.98868458274404
        ],
        [
          402.2072135785007,
          390.98868458274404
        ],
        [
          396.2072135785007,
          374.98868458274404
        ],
        [
          395.7072135785007,
          357.98868458274404
        ],
        [
          397.2072135785007,
          348.98868458274404
        ],
        [
          406.2072135785007,
          324.98868458274404
        ],
        [
          419.2072135785007,
          300.98868458274404
        ],
        [
          428.2072135785007,
          287.988684582744
        ],
        [
          443.7072135785007,
          271.488684582744
        ],
        [
          466.7072135785007,
          257.488684582744
        ],
        [
          501.7072135785007,
          247.48868458274399
        ],
        [
          535.7072135785007,
          243.98868458274399
        ],
        [
          599.7072135785007,
          243.98868458274399
        ],
        [
          626.7072135785005,
          246.48868458274399
        ],
        [
          662.7072135785005,
          255.48868458274399
        ],
        [
          689.707213578501,
          271.488684582744
        ],
        [
          699.2072135785005,
          280.988684582744
        ],
        [
          726.2072135785005,
          322.98868458274404
        ],
        [
          738.207213578501,
          357.98868458274404
        ],
        [
          737.207213578501,
          373.98868458274404
        ],
        [
          725.2072135785005,
          398.98868458274404
        ],
        [
          707.7072135785005,
          413.48868458274404
        ],
        [
          686.707213578501,
          420.48868458274404
        ],
        [
          644.707213578501,
          425.48868458274404
        ],
        [
          603.2301493583171,
          429.17675797723945
        ]
      ],
      "group_id": null,
      "description": "",
      "shape_type": "polygon",
      "flags": {},
      "mask": null
    },
    {
      "label": "body",
      "points": [
        [
          613.0,
          892.5
        ],
        [
          392.0,
          889.5
        ],
        [
          369.0,
          885.5
        ],
        [
          343.0,
          871.5
        ],
        [
          339.0,
          874.5
        ],
        [
          333.0,
          859.5
        ],
        [
          315.5,
          854.0
        ],
        [
          315.5,
          850.0
        ],
        [
          321.0,
          848.5
        ],
        [
          316.0,
          845.5
        ],
        [
          312.0,
          849.5
        ],
        [
          303.0,
          842.5
        ],
        [
          284.5,
          823.0
        ],
        [
          264.5,
          787.0
        ],
        [
          258.5,
          749.0
        ],
        [
          257.0,
          659.0
        ],
        [
          261.5,
          606.0
        ],
        [
          265.5,
          326.0
        ],
        [
          274.5,
          293.0
        ],
        [
          284.5,
          274.0
        ],
        [
          321.0,
          240.5
        ],
        [
          387.0,
          220.5
        ],
        [
          478.0,
          207.5
        ],
        [
          550.0,
          201.0
        ],
        [
          610.0,
          202.5
        ],
        [
          731.0,
          216.5
        ],
        [
          794.0,
          233.5
        ],
        [
          835.0,
          258.5
        ],
        [
          857.5,
          292.0
        ],
        [
          865.5,
          318.0
        ],
        [
          868.5,
          356.0
        ],
        [
          868.5,
          546.0
        ],
        [
          875.5,
          663.0
        ],
        [
          872.5,
          759.0
        ],
        [
          865.5,
          791.0
        ],
        [
          850.5,
          820.0
        ],
        [
          815.0,
          856.5
        ],
        [
          801.0,
          860.5
        ],
        [
          790.0,
          879.5
        ],
        [
          743.0,
          889.5
        ]
      ],
      "group_id": null,
      "description": "",
      "shape_type": "polygon",
      "flags": {},
      "mask": null
    },
    {
      "label": "nose_tip",
      "points": [
        [
          564.3917963224894,
          718.2178217821781
        ]
      ],
      "group_id": null,
      "description": "",
      "shape_type": "point",
      "flags": {},
      "mask": null
    }
  ],
  "imagePath": "df39609d-CRH2C_front_side.001_front.jpeg",
  "imageData": null,
  "imageHeight": 1080,
  "imageWidth": 1150
}