{
  "version": "7.0.4",
  "flags": {},
  "shapes": [
    {
      "label": "windshield",
      "points": [
        [
          520.7633587786261,
          478.2099236641222
        ],
        [
          432.76335877862607,
          474.2099236641222
        ],
        [
          399.76335877862607,
          469.2099236641222
        ],
        [
          382.76335877862607,
          461.2099236641222
        ],
        [
          378.26335877862607,
          454.7099236641222
        ],
        [
          377.26335877862607,
          447.7099236641222
        ],
        [
          379.26335877862607,
          446.7099236641222
        ],
        [
          380.26335877862607,
          431.7099236641222
        ],
        [
          381.26335877862607,
          375.7099236641221
        ],
        [
          385.26335877862607,
          356.70992366412213
        ],
        [
          389.26335877862607,
          351.70992366412213
        ],
        [
          389.26335877862607,
          346.70992366412213
        ],
        [
          405.76335877862607,
          329.2099236641221
        ],
        [
          434.76335877862607,
          312.20992366412213
        ],
        [
          465.76335877862607,
          303.20992366412213
        ],
        [
          499.76335877862607,
          298.20992366412213
        ],
        [
          557.7633587786261,
          297.70992366412213
        ],
        [
          587.7633587786261,
          299.20992366412213
        ],
        [
          623.7633587786261,
          307.20992366412213
        ],
        [
          648.7633587786261,
          317.20992366412213
        ],
        [
          666.7633587786261,
          329.2099236641221
        ],
        [
          681.2633587786261,
          345.70992366412213
        ],
        [
          690.2633587786261,
          364.70992366412213
        ],
        [
          692.2633587786261,
          380.7099236641221
        ],
        [
          691.2633587786261,
          393.70992366412213
        ],
        [
          693.2633587786261,
          396.7099236641221
        ],
        [
          691.2633587786261,
          410.7099236641221
        ],
        [
          694.2633587786261,
          417.7099236641221
        ],
        [
          694.2633587786261,
          423.7099236641222
        ],
        [
          692.2633587786261,
          426.7099236641222
        ],
        [
          694.2633587786261,
          429.7099236641222
        ],
        [
          694.2633587786261,
          452.7099236641222
        ],
        [
          692.2633587786261,
          458.7099236641222
        ],
        [
          681.7633587786261,
          465.2099236641222
        ],
        [
          661.7633587786261,
          471.2099236641222
        ],
        [
          597.1297709923665,
          477.1526717557252
        ]
      ],
      "group_id": null,
      "description": "",
      "shape_type": "polygon",
      "flags": {},
      "mask": null
    },
    {
      "label": "body",
      "points": [
        [
          668.0,
          899.5
        ],
        [
          549.0,
          903.5
        ],
        [
          410.0,
          899.5
        ],
        [
          365.0,
          896.5
        ],
        [
          317.0,
          890.5
        ],
        [
          304.5,
          867.0
        ],
        [
          287.5,
          858.0
        ],
        [
          283.5,
          845.0
        ],
        [
          262.5,
          831.0
        ],
        [
          245.5,
          805.0
        ],
        [
          237.5,
          769.0
        ],
        [
          234.5,
          725.0
        ],
        [
          234.5,
          413.0
        ],
        [
          241.5,
          346.0
        ],
        [
          257.5,
          312.0
        ],
        [
          273.0,
          295.5
        ],
        [
          303.0,
          278.5
        ],
        [
          332.0,
          269.5
        ],
        [
          347.5,
          239.0
        ],
        [
          379.0,
          216.5
        ],
        [
          513.0,
          201.0
        ],
        [
          577.0,
          201.5
        ],
        [
          637.0,
          212.5
        ],
        [
          694.0,
          216.5
        ],
        [
          722.5,
          237.0
        ],
        [
          739.0,
          269.5
        ],
        [
          781.0,
          283.5
        ],
        [
          804.0,
          299.5
        ],
        [
          825.5,
          333.0
        ],
        [
          833.5,
          364.0
        ],
        [
          837.5,
          427.0
        ],
        [
          837.5,
          740.0
        ],
        [
          829.5,
          798.0
        ],
        [
          809.5,
          830.0
        ],
        [
          788.5,
          844.0
        ],
        [
          785.5,
          856.0
        ],
        [
          768.5,
          864.0
        ],
        [
          757.0,
          889.5
        ],
        [
          707.0,
          896.5
        ]
      ],
      "group_id": null,
      "description": "",
      "shape_type": "polygon",
      "flags": {},
      "mask": null
    },
    {
      "label": "nose_tip",
      "points": [
        [
          536.824427480916,
          764.1221374045801
        ]
      ],
      "group_id": null,
      "description": "",
      "shape_type": "point",
      "flags": {},
      "mask": null
    }
  ],
  "imagePath": "c243126c-CRH2E_front_side.008_front.jpeg",
  "imageData": null,
  "imageHeight": 1080,
  "imageWidth": 1008
}