{
  "version": "7.0.4",
  "flags": {},
  "shapes": [
    {
      "label": "windshield",
      "points": [
        [
          591.8414203522857,
          470.53078834722
        ],
        [
          493.8414203522857,
          469.53078834722
        ],
        [
          474.8414203522857,
          465.53078834722
        ],
        [
          465.8414203522857,
          465.53078834722
        ],
        [
          437.8414203522857,
          454.53078834722
        ],
        [
          417.3414203522857,
          431.03078834722
        ],
        [
          407.3414203522857,
          400.0307883472199
        ],
        [
          398.3414203522857,
          383.0307883472199
        ],
        [
          386.8414203522857,
          349.0307883472199
        ],
        [
          386.8414203522857,
          341.0307883472199
        ],
        [
          388.3414203522857,
          337.0307883472199
        ],
        [
          392.8414203522857,
          332.5307883472199
        ],
        [
          398.8414203522857,
          330.5307883472199
        ],
        [
          487.8414203522857,
          326.0307883472199
        ],
        [
          591.8414203522857,
          326.0307883472199
        ],
        [
          644.8414203522857,
          329.5307883472199
        ],
        [
          677.8414203522857,
          329.5307883472199
        ],
        [
          694.8414203522858,
          333.5307883472199
        ],
        [
          700.3414203522858,
          341.0307883472199
        ],
        [
          700.3414203522858,
          352.0307883472199
        ],
        [
          680.3414203522857,
          400.0307883472199
        ],
        [
          679.3414203522857,
          409.0307883472199
        ],
        [
          671.3414203522857,
          429.03078834721987
        ],
        [
          662.3414203522857,
          443.03078834722
        ],
        [
          640.8414203522857,
          459.53078834722
        ],
        [
          634.8414203522857,
          459.53078834722
        ],
        [
          617.8414203522857,
          466.53078834722
        ]
      ],
      "group_id": null,
      "description": "",
      "shape_type": "polygon",
      "flags": {},
      "mask": null
    },
    {
      "label": "body",
      "points": [
        [
          670.0,
          841.5
        ],
        [
          410.09302325581405,
          842.7562446167098
        ],
        [
          382.0,
          841.5
        ],
        [
          340.0,
          840.5
        ],
        [
          331.5,
          837.0
        ],
        [
          269.5,
          706.0
        ],
        [
          257.5,
          648.0
        ],
        [
          256.0,
          576.0
        ],
        [
          285.5,
          313.0
        ],
        [
          295.5,
          288.0
        ],
        [
          323.5,
          255.0
        ],
        [
          337.5,
          208.0
        ],
        [
          346.0,
          194.5
        ],
        [
          741.0,
          196.5
        ],
        [
          749.5,
          206.0
        ],
        [
          764.5,
          257.0
        ],
        [
          794.5,
          293.0
        ],
        [
          807.5,
          345.0
        ],
        [
          816.5,
          466.0
        ],
        [
          825.5,
          529.0
        ],
        [
          824.5,
          655.0
        ],
        [
          807.5,
          723.0
        ],
        [
          767.5,
          795.0
        ],
        [
          745.0,
          841.5
        ],
        [
          701.6520241171404,
          839.7416020671835
        ]
      ],
      "group_id": null,
      "description": "",
      "shape_type": "polygon",
      "flags": {},
      "mask": null
    },
    {
      "label": "nose_tip",
      "points": [
        [
          539.2919896640827,
          679.1042204995694
        ]
      ],
      "group_id": null,
      "description": "",
      "shape_type": "point",
      "flags": {},
      "mask": null
    }
  ],
  "imagePath": "f38fad77-CRH5E-Side_Front_front.jpg",
  "imageData": null,
  "imageHeight": 1080,
  "imageWidth": 1076
}